setup.py
nested_query_string/__init__.py
nested_query_string/nested_query_string.py
nested_query_string/version.py
nested_query_string.egg-info/PKG-INFO
nested_query_string.egg-info/SOURCES.txt
nested_query_string.egg-info/dependency_links.txt
nested_query_string.egg-info/top_level.txt