Metadata-Version: 1.1
Name: nested-query-string
Version: 0.0.1
Summary: Generate nested query strings similar to rack and node qs
Home-page: https://github.com/cine-io/nested-query-string
Author: Cine.io Engineering
Author-email: engineering@cine.io
License: MIT
Platform: UNKNOWN
Classifier: License :: OSI Approved :: MIT License
Classifier: Programming Language :: Python
Classifier: Development Status :: 3 - Alpha
Classifier: Intended Audience :: Developers
Classifier: Topic :: Internet
